{
	"entryComponent": 0,
	"componentRegistry": {
		"dataType": "Map",
		"value": [
			[
				0,
				{
					"nInputs": 2,
					"nOutputs": 2,
					"state": {
						"components": [],
						"connections": {
							"dataType": "Set",
							"value": [
								{
									"source": {
										"component": "input",
										"pin": 1
									},
									"destination": {
										"component": "output",
										"pin": 0
									}
								},
								{
									"source": {
										"component": "input",
										"pin": 0
									},
									"destination": {
										"component": "output",
										"pin": 1
									}
								}
							]
						}
					},
					"style": {
						"name": "FancyPants"
					}
				}
			]
		]
	}
}